spcq.py
spcq-0.0.1.dist-info/METADATA
spcq-0.0.1.dist-info/WHEEL
spcq-0.0.1.dist-info/top_level.txt
spcq-0.0.1.dist-info/RECORD
