Metadata-Version: 2.1
Name: spcq
Version: 0.0.1
Summary: Query Sindh police complaint database.
Home-page: https://www.techtum.dev
Author: siphr
Author-email: pypi@techtum.dev
License: UNKNOWN
Project-URL: Bug Tracker, https://github.com/
Platform: UNKNOWN
Classifier: Programming Language :: Python :: 3
Classifier: License :: OSI Approved :: MIT License
Classifier: Operating System :: OS Independent
Requires-Python: >=3.6
